{
  "uid": "ai-v2-overview",
  "title": "AI v2 Overview",
  "description": "Comprehensive monitoring dashboard for the AI v2 project",
  "editable": true,
  "schemaVersion": 39,
  "version": 1,
  "time": {
    "from": "now-1h",
    "to": "now"
  },
  "refresh": "15s",
  "timezone": "browser",
  "panels": [
    {
      "type": "row",
      "title": "API Request Metrics",
      "gridPos": { "h": 1, "w": 24, "x": 0, "y": 0 },
      "collapsed": false,
      "id": 100
    },
    {
      "id": 1,
      "type": "timeseries",
      "title": "Request Rate",
      "gridPos": { "h": 8, "w": 6, "x": 0, "y": 1 },
      "datasource": { "type": "prometheus", "uid": "prometheus" },
      "fieldConfig": {
        "defaults": {
          "unit": "reqps",
          "custom": {
            "drawStyle": "line",
            "lineWidth": 1,
            "fillOpacity": 10,
            "pointSize": 5,
            "showPoints": "never",
            "spanNulls": false
          }
        },
        "overrides": []
      },
      "options": {
        "tooltip": { "mode": "multi" },
        "legend": { "displayMode": "table", "placement": "bottom" }
      },
      "targets": [
        {
          "expr": "rate(http_requests_total[1m])",
          "legendFormat": "{{method}} {{path}} {{status}}",
          "refId": "A"
        }
      ]
    },
    {
      "id": 2,
      "type": "timeseries",
      "title": "Request Latency P50/P95/P99",
      "gridPos": { "h": 8, "w": 6, "x": 6, "y": 1 },
      "datasource": { "type": "prometheus", "uid": "prometheus" },
      "fieldConfig": {
        "defaults": {
          "unit": "s",
          "custom": {
            "drawStyle": "line",
            "lineWidth": 1,
            "fillOpacity": 10,
            "pointSize": 5,
            "showPoints": "never",
            "spanNulls": false
          }
        },
        "overrides": []
      },
      "options": {
        "tooltip": { "mode": "multi" },
        "legend": { "displayMode": "table", "placement": "bottom" }
      },
      "targets": [
        {
          "expr": "histogram_quantile(0.50, sum(rate(http_request_duration_seconds_bucket[1m])) by (le))",
          "legendFormat": "p50",
          "refId": "A"
        },
        {
          "expr": "histogram_quantile(0.95, sum(rate(http_request_duration_seconds_bucket[1m])) by (le))",
          "legendFormat": "p95",
          "refId": "B"
        },
        {
          "expr": "histogram_quantile(0.99, sum(rate(http_request_duration_seconds_bucket[1m])) by (le))",
          "legendFormat": "p99",
          "refId": "C"
        }
      ]
    },
    {
      "id": 3,
      "type": "timeseries",
      "title": "Error Rate (5xx)",
      "gridPos": { "h": 8, "w": 6, "x": 12, "y": 1 },
      "datasource": { "type": "prometheus", "uid": "prometheus" },
      "fieldConfig": {
        "defaults": {
          "unit": "reqps",
          "custom": {
            "drawStyle": "line",
            "lineWidth": 1,
            "fillOpacity": 10,
            "pointSize": 5,
            "showPoints": "never",
            "spanNulls": false
          },
          "color": { "mode": "fixed", "fixedColor": "red" }
        },
        "overrides": []
      },
      "options": {
        "tooltip": { "mode": "multi" },
        "legend": { "displayMode": "table", "placement": "bottom" }
      },
      "targets": [
        {
          "expr": "rate(http_requests_total{status=~\"5..\"}[1m])",
          "legendFormat": "{{method}} {{path}} {{status}}",
          "refId": "A"
        }
      ]
    },
    {
      "id": 4,
      "type": "timeseries",
      "title": "Active Requests",
      "gridPos": { "h": 8, "w": 6, "x": 18, "y": 1 },
      "datasource": { "type": "prometheus", "uid": "prometheus" },
      "fieldConfig": {
        "defaults": {
          "unit": "short",
          "custom": {
            "drawStyle": "line",
            "lineWidth": 1,
            "fillOpacity": 10,
            "pointSize": 5,
            "showPoints": "never",
            "spanNulls": false
          }
        },
        "overrides": []
      },
      "options": {
        "tooltip": { "mode": "multi" },
        "legend": { "displayMode": "table", "placement": "bottom" }
      },
      "targets": [
        {
          "expr": "http_requests_in_progress",
          "legendFormat": "active requests",
          "refId": "A"
        }
      ]
    },
    {
      "type": "row",
      "title": "Agent Sandbox Metrics",
      "gridPos": { "h": 1, "w": 24, "x": 0, "y": 9 },
      "collapsed": false,
      "id": 101
    },
    {
      "id": 5,
      "type": "timeseries",
      "title": "Agent Sessions",
      "gridPos": { "h": 8, "w": 8, "x": 0, "y": 10 },
      "datasource": { "type": "prometheus", "uid": "prometheus" },
      "fieldConfig": {
        "defaults": {
          "unit": "short",
          "custom": {
            "drawStyle": "line",
            "lineWidth": 1,
            "fillOpacity": 10,
            "pointSize": 5,
            "showPoints": "never",
            "spanNulls": false
          }
        },
        "overrides": []
      },
      "options": {
        "tooltip": { "mode": "multi" },
        "legend": { "displayMode": "table", "placement": "bottom" }
      },
      "targets": [
        {
          "expr": "agent_sessions_active",
          "legendFormat": "active sessions",
          "refId": "A"
        }
      ]
    },
    {
      "id": 6,
      "type": "timeseries",
      "title": "Agent Executions",
      "gridPos": { "h": 8, "w": 8, "x": 8, "y": 10 },
      "datasource": { "type": "prometheus", "uid": "prometheus" },
      "fieldConfig": {
        "defaults": {
          "unit": "ops",
          "custom": {
            "drawStyle": "line",
            "lineWidth": 1,
            "fillOpacity": 10,
            "pointSize": 5,
            "showPoints": "never",
            "spanNulls": false
          }
        },
        "overrides": []
      },
      "options": {
        "tooltip": { "mode": "multi" },
        "legend": { "displayMode": "table", "placement": "bottom" }
      },
      "targets": [
        {
          "expr": "rate(agent_executions_total[1m])",
          "legendFormat": "{{harness}} {{status}}",
          "refId": "A"
        }
      ]
    },
    {
      "id": 7,
      "type": "timeseries",
      "title": "Agent Execution Duration",
      "gridPos": { "h": 8, "w": 8, "x": 16, "y": 10 },
      "datasource": { "type": "prometheus", "uid": "prometheus" },
      "fieldConfig": {
        "defaults": {
          "unit": "s",
          "custom": {
            "drawStyle": "line",
            "lineWidth": 1,
            "fillOpacity": 10,
            "pointSize": 5,
            "showPoints": "never",
            "spanNulls": false
          }
        },
        "overrides": []
      },
      "options": {
        "tooltip": { "mode": "multi" },
        "legend": { "displayMode": "table", "placement": "bottom" }
      },
      "targets": [
        {
          "expr": "histogram_quantile(0.50, sum(rate(agent_execution_duration_seconds_bucket[1m])) by (le))",
          "legendFormat": "p50",
          "refId": "A"
        },
        {
          "expr": "histogram_quantile(0.95, sum(rate(agent_execution_duration_seconds_bucket[1m])) by (le))",
          "legendFormat": "p95",
          "refId": "B"
        },
        {
          "expr": "histogram_quantile(0.99, sum(rate(agent_execution_duration_seconds_bucket[1m])) by (le))",
          "legendFormat": "p99",
          "refId": "C"
        }
      ]
    },
    {
      "type": "row",
      "title": "ETL Pipeline Metrics",
      "gridPos": { "h": 1, "w": 24, "x": 0, "y": 18 },
      "collapsed": false,
      "id": 102
    },
    {
      "id": 8,
      "type": "timeseries",
      "title": "ETL Records Synced",
      "gridPos": { "h": 8, "w": 8, "x": 0, "y": 19 },
      "datasource": { "type": "prometheus", "uid": "prometheus" },
      "fieldConfig": {
        "defaults": {
          "unit": "ops",
          "custom": {
            "drawStyle": "line",
            "lineWidth": 1,
            "fillOpacity": 10,
            "pointSize": 5,
            "showPoints": "never",
            "spanNulls": false
          }
        },
        "overrides": []
      },
      "options": {
        "tooltip": { "mode": "multi" },
        "legend": { "displayMode": "table", "placement": "bottom" }
      },
      "targets": [
        {
          "expr": "rate(etl_records_synced_total[1m])",
          "legendFormat": "{{source}}",
          "refId": "A"
        }
      ]
    },
    {
      "id": 9,
      "type": "timeseries",
      "title": "ETL Cycle Duration",
      "gridPos": { "h": 8, "w": 8, "x": 8, "y": 19 },
      "datasource": { "type": "prometheus", "uid": "prometheus" },
      "fieldConfig": {
        "defaults": {
          "unit": "s",
          "custom": {
            "drawStyle": "line",
            "lineWidth": 1,
            "fillOpacity": 10,
            "pointSize": 5,
            "showPoints": "never",
            "spanNulls": false
          }
        },
        "overrides": []
      },
      "options": {
        "tooltip": { "mode": "multi" },
        "legend": { "displayMode": "table", "placement": "bottom" }
      },
      "targets": [
        {
          "expr": "etl_cycle_duration_seconds",
          "legendFormat": "cycle duration",
          "refId": "A"
        }
      ]
    },
    {
      "id": 10,
      "type": "timeseries",
      "title": "ETL Errors",
      "gridPos": { "h": 8, "w": 8, "x": 16, "y": 19 },
      "datasource": { "type": "prometheus", "uid": "prometheus" },
      "fieldConfig": {
        "defaults": {
          "unit": "ops",
          "custom": {
            "drawStyle": "line",
            "lineWidth": 1,
            "fillOpacity": 10,
            "pointSize": 5,
            "showPoints": "never",
            "spanNulls": false
          },
          "color": { "mode": "fixed", "fixedColor": "red" }
        },
        "overrides": []
      },
      "options": {
        "tooltip": { "mode": "multi" },
        "legend": { "displayMode": "table", "placement": "bottom" }
      },
      "targets": [
        {
          "expr": "rate(etl_errors_total[1m])",
          "legendFormat": "{{source}}",
          "refId": "A"
        }
      ]
    },
    {
      "type": "row",
      "title": "Infrastructure",
      "gridPos": { "h": 1, "w": 24, "x": 0, "y": 27 },
      "collapsed": false,
      "id": 103
    },
    {
      "id": 11,
      "type": "timeseries",
      "title": "Postgres Connections",
      "gridPos": { "h": 8, "w": 8, "x": 0, "y": 28 },
      "datasource": { "type": "prometheus", "uid": "prometheus" },
      "fieldConfig": {
        "defaults": {
          "unit": "short",
          "custom": {
            "drawStyle": "line",
            "lineWidth": 1,
            "fillOpacity": 10,
            "pointSize": 5,
            "showPoints": "never",
            "spanNulls": false
          }
        },
        "overrides": []
      },
      "options": {
        "tooltip": { "mode": "multi" },
        "legend": { "displayMode": "table", "placement": "bottom" }
      },
      "targets": [
        {
          "expr": "pg_stat_activity_count",
          "legendFormat": "{{datname}} - {{state}}",
          "refId": "A"
        }
      ]
    },
    {
      "id": 12,
      "type": "timeseries",
      "title": "Redis Memory",
      "gridPos": { "h": 8, "w": 8, "x": 8, "y": 28 },
      "datasource": { "type": "prometheus", "uid": "prometheus" },
      "fieldConfig": {
        "defaults": {
          "unit": "bytes",
          "custom": {
            "drawStyle": "line",
            "lineWidth": 1,
            "fillOpacity": 10,
            "pointSize": 5,
            "showPoints": "never",
            "spanNulls": false
          }
        },
        "overrides": []
      },
      "options": {
        "tooltip": { "mode": "multi" },
        "legend": { "displayMode": "table", "placement": "bottom" }
      },
      "targets": [
        {
          "expr": "redis_memory_used_bytes",
          "legendFormat": "memory used",
          "refId": "A"
        }
      ]
    },
    {
      "id": 13,
      "type": "timeseries",
      "title": "Redis Connected Clients",
      "gridPos": { "h": 8, "w": 8, "x": 16, "y": 28 },
      "datasource": { "type": "prometheus", "uid": "prometheus" },
      "fieldConfig": {
        "defaults": {
          "unit": "short",
          "custom": {
            "drawStyle": "line",
            "lineWidth": 1,
            "fillOpacity": 10,
            "pointSize": 5,
            "showPoints": "never",
            "spanNulls": false
          }
        },
        "overrides": []
      },
      "options": {
        "tooltip": { "mode": "multi" },
        "legend": { "displayMode": "table", "placement": "bottom" }
      },
      "targets": [
        {
          "expr": "redis_connected_clients",
          "legendFormat": "connected clients",
          "refId": "A"
        }
      ]
    },
    {
      "type": "row",
      "title": "Logs",
      "gridPos": { "h": 1, "w": 24, "x": 0, "y": 36 },
      "collapsed": false,
      "id": 104
    },
    {
      "id": 14,
      "type": "logs",
      "title": "Service Logs",
      "gridPos": { "h": 10, "w": 24, "x": 0, "y": 37 },
      "datasource": { "type": "victoriametrics-logs-datasource", "uid": "victorialogs" },
      "options": {
        "showTime": true,
        "showLabels": true,
        "showCommonLabels": false,
        "wrapLogMessage": true,
        "prettifyLogMessage": false,
        "enableLogDetails": true,
        "sortOrder": "Descending",
        "dedupStrategy": "none"
      },
      "targets": [
        {
          "expr": "*",
          "legendFormat": "",
          "refId": "A"
        }
      ]
    }
  ],
  "templating": {
    "list": [
      {
        "name": "service",
        "type": "query",
        "datasource": { "type": "victoriametrics-logs-datasource", "uid": "victorialogs" },
        "query": "service",
        "refresh": 2,
        "includeAll": true,
        "multi": true,
        "current": {
          "selected": true,
          "text": "All",
          "value": "$__all"
        }
      }
    ]
  },
  "annotations": {
    "list": []
  },
  "links": [],
  "tags": ["ai-v2", "monitoring"]
}
